{
  "variants": {
    "age=0": {
      "model": "productivetrees:block/fruit/almond/stage_0"
    },
    "age=1": {
      "model": "productivetrees:block/fruit/almond/stage_1"
    },
    "age=2": {
      "model": "productivetrees:block/fruit/almond/stage_2"
    },
    "age=3": {
      "model": "productivetrees:block/fruit/almond/stage_3"
    },
    "age=4": {
      "model": "productivetrees:block/fruit/almond/stage_4"
    },
    "age=5": {
      "model": "productivetrees:block/fruit/almond/stage_5"
    },
    "age=6": {
      "model": "productivetrees:block/fruit/almond/stage_6"
    },
    "age=7": {
      "model": "productivetrees:block/fruit/almond/stage_7"
    }
  }
}