{
  "parent": "minecraft:recipes/root",
  "criteria": {
    "has_logs": {
      "conditions": {
        "items": [
          {
            "items": [
              "productivetrees:brazil_nut_log",
              "productivetrees:brazil_nut_wood",
              "productivetrees:brazil_nut_stripped_log",
              "productivetrees:brazil_nut_stripped_wood"
            ]
          }
        ]
      },
      "trigger": "minecraft:inventory_changed"
    },
    "has_the_recipe": {
      "conditions": {
        "recipe": "productivetrees:planks/brazil_nut_planks"
      },
      "trigger": "minecraft:recipe_unlocked"
    }
  },
  "requirements": [
    [
      "has_logs",
      "has_the_recipe"
    ]
  ],
  "rewards": {
    "recipes": [
      "productivetrees:planks/brazil_nut_planks"
    ]
  },
  "sends_telemetry_event": false
}