{
  "parent": "minecraft:recipes/root",
  "criteria": {
    "has_sycamore_fig_planks": {
      "conditions": {
        "items": [
          {
            "items": "productivetrees:sycamore_fig_planks"
          }
        ]
      },
      "trigger": "minecraft:inventory_changed"
    },
    "has_the_recipe": {
      "conditions": {
        "recipe": "productivetrees:door/sycamore_fig_door"
      },
      "trigger": "minecraft:recipe_unlocked"
    }
  },
  "requirements": [
    [
      "has_the_recipe",
      "has_sycamore_fig_planks"
    ]
  ],
  "rewards": {
    "recipes": [
      "productivetrees:door/sycamore_fig_door"
    ]
  }
}