{
  "parent": "minecraft:recipes/root",
  "criteria": {
    "has_sparkling_cherry": {
      "conditions": {
        "items": [
          {
            "items": "productivetrees:sparkling_cherry"
          }
        ]
      },
      "trigger": "minecraft:inventory_changed"
    },
    "has_the_recipe": {
      "conditions": {
        "recipe": "productivetrees:crates/sparkling_cherry_crate"
      },
      "trigger": "minecraft:recipe_unlocked"
    }
  },
  "requirements": [
    [
      "has_the_recipe",
      "has_sparkling_cherry"
    ]
  ],
  "rewards": {
    "recipes": [
      "productivetrees:crates/sparkling_cherry_crate"
    ]
  }
}