{
  "type": "forge:conditional",
  "recipes": [
    {
      "conditions": [
        {
          "type": "forge:mod_loaded",
          "modid": "corail_woodcutter"
        }
      ],
      "recipe": {
        "type": "corail_woodcutter:woodcutting",
        "count": 8,
        "ingredient": [
          {
            "item": "productivetrees:coffea_log"
          },
          {
            "item": "productivetrees:coffea_wood"
          },
          {
            "item": "productivetrees:coffea_stripped_log"
          },
          {
            "item": "productivetrees:coffea_stripped_wood"
          }
        ],
        "result": "minecraft:stick"
      }
    }
  ]
}